hwdocs_mcp/__init__.py
hwdocs_mcp/cli.py
hwdocs_mcp/client.py
hwdocs_mcp/config.py
hwdocs_mcp/server.py
hwdocs_mcp-0.1.2.dist-info/METADATA
hwdocs_mcp-0.1.2.dist-info/WHEEL
hwdocs_mcp-0.1.2.dist-info/entry_points.txt
hwdocs_mcp-0.1.2.dist-info/RECORD
