Metadata-Version: 2.4
Name: hwdocs-mcp
Version: 0.1.2
Summary: MCP server for hardware documentation search and management
Project-URL: Homepage, https://github.com/run-llama/semtools
Project-URL: Documentation, https://github.com/run-llama/semtools#readme
Project-URL: Repository, https://github.com/run-llama/semtools
Project-URL: Issues, https://github.com/run-llama/semtools/issues
Author-email: LlamaIndex <logan@runllama.ai>
License: MIT
Keywords: ai,claude,cursor,documentation,embedded,hardware,mcp
Classifier: Development Status :: 4 - Beta
Classifier: Intended Audience :: Developers
Classifier: License :: OSI Approved :: MIT License
Classifier: Programming Language :: Python :: 3
Classifier: Programming Language :: Python :: 3.10
Classifier: Programming Language :: Python :: 3.11
Classifier: Programming Language :: Python :: 3.12
Classifier: Topic :: Software Development :: Documentation
Requires-Python: >=3.10
Requires-Dist: httpx>=0.27.0
Requires-Dist: mcp>=1.0.0
Requires-Dist: pydantic-settings>=2.0.0
Requires-Dist: pydantic>=2.0.0
Provides-Extra: dev
Requires-Dist: pytest-asyncio>=0.24.0; extra == 'dev'
Requires-Dist: pytest>=8.0.0; extra == 'dev'
Requires-Dist: ruff>=0.8.0; extra == 'dev'
